incendio/__init__.py
incendio/_nbdev.py
incendio/callbacks.py
incendio/core.py
incendio/data.py
incendio/fast_utils.py
incendio/layers.py
incendio/lightning_utils.py
incendio/losses.py
incendio/metrics.py
incendio/nlp.py
incendio/optimizers.py
incendio/utils.py
incendio-0.14.0.dist-info/LICENSE
incendio-0.14.0.dist-info/METADATA
incendio-0.14.0.dist-info/WHEEL
incendio-0.14.0.dist-info/top_level.txt
incendio-0.14.0.dist-info/RECORD
